dae_RelayBoard/FTD2XXDllWrap.py
dae_RelayBoard/FTD2XXLinux.py
dae_RelayBoard/FTD2XXWindows.py
dae_RelayBoard/__init__.py
dae_RelayBoard/dae_RelayBoard.py
dae_RelayBoard/dae_RelayBoard_Common.py
dae_RelayBoard/dae_RelayBoard_D2XX.py
dae_RelayBoard/dae_RelayBoard_VCP.py
dae_RelayBoard-1.5.2.dist-info/METADATA
dae_RelayBoard-1.5.2.dist-info/WHEEL
dae_RelayBoard-1.5.2.dist-info/top_level.txt
dae_RelayBoard-1.5.2.dist-info/RECORD
