Metadata-Version: 2.1
Name: dae_RelayBoard
Version: 1.5.2
Summary: Denkovi Relay Board Controller
Home-page: https://code.google.com/p/dae-py-relay-controller/
Author: Peter Bingham
Author-email: petersbingham@hotmail.co.uk
